facebooklikes
