Metadata-Version: 1.1
Name: facebooklikes
Version: 0.1.0
Summary: Fetch facebook likes for page or facebook url
Home-page: https://github.com/sloev/facebooklikes
Author: sloev
Author-email: johannes.valbjorn+facebooklikes@gmail.com
License: UNKNOWN
Keywords: facebook likes
Platform: UNKNOWN
Classifier: Development Status :: 2 - Pre-Alpha
Classifier: Intended Audience :: Developers
Classifier: Natural Language :: English
Classifier: Programming Language :: Python :: 2.7
Classifier: Programming Language :: Python :: 3.5
Classifier: Programming Language :: Python :: 3.6
